{
    "rocky rumble": {
        "time_given": "2023-09-01 16:08:30 (UTC)",
        "proof": "https://x.com/mcnintendo9/status/1698052998843470254?s=46"
    },
    "sphinx hijinx": {
        "time_given": "2023-09-01 16:12:24 (UTC)",
        "proof": "https://x.com/mcnintendo9/status/1486735704835067916?s=46"
    },
    "rocket hop": {
        "time_given": "2023-09-01 16:12:47 (UTC)",
        "proof": "https://x.com/mcnintendo9/status/1486083338041393153?s=46"
    },
    "hedge rendezvous": {
        "time_given": "2023-09-01 16:13:19 (UTC)",
        "proof": "https://x.com/mcnintendo9/status/1482729991431356416?s=46"
    },
    "lake skip": {
        "time_given": "2023-09-01 16:13:34 (UTC)",
        "proof": "https://x.com/mcnintendo9/status/1482329859116339200?s=46"
    },
    "winner's gambit": {
        "time_given": "2023-09-01 16:16:14 (UTC)",
        "proof": "https://x.com/mcnintendo9/status/1482089441892073473?s=46"
    },
    "seaside dram": {
        "time_given": "2023-09-01 16:16:43 (UTC)",
        "proof": "https://x.com/mcnintendo9/status/1481766383473991680?s=12"
    },
    "fruity gap": {
        "time_given": "2023-09-01 16:17:03 (UTC)",
        "proof": "https://x.com/mcnintendo9/status/1480191174392516615?s=46"
    },
    "frogless": {
        "time_given": "2023-09-01 16:17:33 (UTC)",
        "proof": "https://x.com/mcnintendo9/status/1479909647066796034?s=12"
    },
    "fork room": {
        "time_given": "2023-09-01 16:17:49 (UTC)",
        "proof": "https://x.com/mcnintendo9/status/1479826943809777665?s=46"
    },
    "flower road skip": {
        "time_given": "2023-09-01 16:18:03 (UTC)",
        "proof": "https://x.com/mcnintendo9/status/1479822468495773701?s=46"
    },
    "meme tree": {
        "time_given": "2023-09-01 16:18:21 (UTC)",
        "proof": "https://x.com/mcnintendo9/status/1479816618674847747?s=46"
    },
    "dark side impossible": {
        "time_given": "2023-09-01 16:18:37 (UTC)",
        "proof": "https://x.com/mcnintendo9/status/1479814217423200256?s=46"
    },
    "flower power": {
        "time_given": "2023-09-01 16:18:49 (UTC)",
        "proof": "https://x.com/mcnintendo9/status/1479808210089381888?s=46"
    },
    "neighbourhood bypass": {
        "time_given": "2023-09-01 16:19:49 (UTC)",
        "proof": "https://x.com/mcnintendo9/status/1479804919980847105?s=46"
    },
    "beetle bypass": {
        "time_given": "2023-09-01 16:20:32 (UTC)",
        "proof": "https://x.com/mcnintendo9/status/1479802034295508992?s=46"
    },
    "bowser bruncheon": {
        "time_given": "2023-09-01 16:22:54 (UTC)",
        "proof": "https://x.com/mcnintendo9/status/1479799852712169473?s=46"
    },
    "cafe cut": {
        "time_given": "2023-09-01 16:23:14 (UTC)",
        "proof": "https://x.com/mcnintendo9/status/1479791028412420098?s=46"
    },
    "metro impossible": {
        "time_given": "2023-09-01 16:23:38 (UTC)",
        "proof": "https://x.com/mcnintendo9/status/1479790874129158147?s=46"
    },
    "forest flip": {
        "time_given": "2023-09-01 16:23:51 (UTC)",
        "proof": "https://x.com/mcnintendo9/status/1479600927812194305?s=46"
    },
    "iron ramp impossible": {
        "time_given": "2023-09-01 16:24:13 (UTC)",
        "proof": "https://x.com/mcnintendo9/status/1479600664346988544?s=46"
    },
    "galactic gorge": {
        "time_given": "2023-09-02 19:32:25 (UTC)",
        "proof": "https://x.com/mcnintendo9/status/1698053381414359281?s=46"
    },
    "abyssal leap": {
        "time_given": "2023-09-02 19:34:25 (UTC)",
        "proof": "https://x.com/mcnintendo9/status/1698056727714042032?s=46"
    }
}